README.rst
setup.py
PyScanii/__init__.py
PyScanii/core.py
PyScanii.egg-info/PKG-INFO
PyScanii.egg-info/SOURCES.txt
PyScanii.egg-info/dependency_links.txt
PyScanii.egg-info/requires.txt
PyScanii.egg-info/top_level.txt