Metadata-Version: 1.1
Name: PyScanii
Version: 1.1.4
Summary: A Python wrapper for Scanii.com
Home-page: http://github.com/smeggingsmegger/PyScanii
Author: Scott Blevins
Author-email: sblevins@gmail.com
License: MIT
Keywords: Scan,Virus,Scanii,API
Platform: OS Independent
Classifier: Development Status :: 3 - Alpha
Classifier: License :: OSI Approved :: MIT License
Classifier: Operating System :: OS Independent
Classifier: Programming Language :: Python :: 2.7
Classifier: Intended Audience :: Developers
Classifier: Topic :: Software Development :: Libraries :: Python Modules
